spycio/.ipynb_checkpoints/euler_diagram-checkpoint.ipynb
spycio/__init__.py
spycio/spycio.py
spycio/utils.py
spycio-0.2.8.dist-info/LICENSE
spycio-0.2.8.dist-info/METADATA
spycio-0.2.8.dist-info/WHEEL
spycio-0.2.8.dist-info/RECORD
