Metadata-Version: 2.1
Name: spycio
Version: 0.2.8
Summary: Distances in python
Home-page: https://pypi.org/project/spycio/
License: MIT
Keywords: distance
Author: Bruno Peixoto
Author-email: brunolnetto@gmail.com
Requires-Python: >=3.8.1,<4.0
Classifier: Development Status :: 1 - Planning
Classifier: Intended Audience :: Developers
Classifier: License :: OSI Approved :: MIT License
Classifier: Natural Language :: English
Classifier: Programming Language :: Python :: 3
Classifier: Programming Language :: Python :: 3.9
Classifier: Programming Language :: Python :: 3.10
Classifier: Programming Language :: Python :: 3.11
Classifier: Programming Language :: Python :: 3 :: Only
Classifier: Topic :: Scientific/Engineering :: Information Analysis
Requires-Dist: docutils (==0.18.1)
Requires-Dist: numpy (>=1.24.1,<2.0.0)
Requires-Dist: pytest-testmon (>=2.0.2,<3.0.0)
Requires-Dist: sphinx-rtd-theme (>=1.2.0,<2.0.0)
Requires-Dist: toml (>=0.10.2,<0.11.0)
Requires-Dist: types-toml (>=0.10.8.5,<0.11.0.0)
Project-URL: Repository, https://github.com/trouchet/spycio
